setup.py
wtfuzz/__init__.py
wtfuzz/wtfuzz.py
wtfuzz.egg-info/PKG-INFO
wtfuzz.egg-info/SOURCES.txt
wtfuzz.egg-info/dependency_links.txt
wtfuzz.egg-info/entry_points.txt
wtfuzz.egg-info/requires.txt
wtfuzz.egg-info/top_level.txt