Metadata-Version: 1.0
Name: wtfuzz
Version: 0.0.12
Summary: A cli tool used for checking the existance of different types of web resources
Home-page: https://github.com/mattjegan/wtfuzz
Author: Matthew Egan
Author-email: matthewj.egan@hotmail.com
License: UNKNOWN
Platform: UNKNOWN
